pg_requests/__init__.py
pg_requests/exceptions.py
pg_requests/functions.py
pg_requests/operators.py
pg_requests/query.py
pg_requests/tokens.py
pg_requests-0.1.0.dist-info/DESCRIPTION.rst
pg_requests-0.1.0.dist-info/METADATA
pg_requests-0.1.0.dist-info/RECORD
pg_requests-0.1.0.dist-info/WHEEL
pg_requests-0.1.0.dist-info/metadata.json
pg_requests-0.1.0.dist-info/top_level.txt
