Metadata-Version: 2.0
Name: pg-requests
Version: 0.1.0
Summary: PostgreSQL-specific query builder library
Home-page: https://github.com/prawn-cake/pg_requests
Author: Maksim Ekimovskii
Author-email: ekimovsky.maksim@gmail.com
License: MIT
Platform: UNKNOWN
